[{"chunk_id": "info_580c43", "title": "Abhiram Kumar Verma - Quick Facts", "text": "Abhiram Kumar Verma\nDepartment | Mining Engineering\nResearch Area(s) | Rock Mechanics and Ground Control Numerical Modeling Slope Design Rock Fracture Mechanics\nYear Joined | 2010\nemail | [email protected]", "page": "Abhiram Kumar Verma"}, {"chunk_id": "30051c2f", "title": "See Also", "text": "\u2022 Department of Mining Engineering", "page": "Abhiram Kumar Verma"}, {"chunk_id": "c5a0016b", "title": "External links", "text": "\u2022 Abhiram Kumar Verma on iitkgp.ac.in", "page": "Abhiram Kumar Verma"}]