[{"chunk_id": "info_62b1c7", "title": "AG31024: Electronic Application In Agriculture - Quick Facts", "text": "AG31024\nCourse name | Electronic Application In Agriculture\nOffered by | Agricultural & Food Engineering\nCredits | 3\nL-T-P | 3-0-0\nPrevious Year Grade Distribution\n{{{grades}}}\nSemester | Spring", "page": "AG31024: Electronic Application In Agriculture"}, {"chunk_id": "77357a9a", "title": "Syllabus mentioned in ERP", "text": "Electronic measurement of engine speed, torque, wheel slip and fuel consumption; Force sensing in upper and lower links of tractors; Microprocesser based engine monitoring system; Controlled environment for crop production, soil conductivity and moisture measurement; Electronic speed counter / monitoring, remote control valves, measurement of nutrient status of crop and soil; Photovoltaic calls for solar energy utilization; Electronic safety relay circuits in tractor and farm machines.", "page": "AG31024: Electronic Application In Agriculture"}]