[{"chunk_id": "info_a4697f", "title": "AG60107: Agro - Quick Facts", "text": "AG60107\nCourse name | AGRO\nOffered by | Agricultural & Food Engineering\nCredits | 4\nL-T-P | 3-1-0\nPrevious Year Grade Distribution\n{{{grades}}}\nSemester | {{{semester}}}", "page": "AG60107: Agro"}, {"chunk_id": "b619cc40", "title": "Syllabus mentioned in ERP", "text": "Methods of techno-economic feasibility study, analysis of alternatives, economic decisions, plant location and layout criteria for selection, single, multiple and continuous facility design and layout problems, discrete location and layout problems, forecasting-distribution of time series analysis and calculations, project feasibility report preparation, agro-industrial production systems- capital budgeting, productivity measurement, quality control inventory, risk analysis, maintenance.", "page": "AG60107: Agro"}]