[{"chunk_id": "info_80487b", "title": "Debasis Samanta - Quick Facts", "text": "Debasis Samanta\nDepartment | Information Technology\nResearch Area(s) | Human Computer Interaction Biometric Based Security Computational Intelligence Big Data Analysis Brain Computing Interaction\nYear Joined | 2004\nemail | [email protected]\nWebsite | http://www.nid.iitkgp.ernet.in/dsamanta/", "page": "Debasis Samanta"}, {"chunk_id": "b6155260", "title": "See Also", "text": "\u2022 Department of Information Technology", "page": "Debasis Samanta"}, {"chunk_id": "24fc4607", "title": "External links", "text": "\u2022 Debasis Samanta on iitkgp.ac.in", "page": "Debasis Samanta"}]