[{"chunk_id": "info_9ef38c", "title": "EC60081: Rf Components And Circuit Design - Quick Facts", "text": "EC60081\nCourse name | Rf Components And Circuit Design\nOffered by | Electronics & Electrical Communication Engineering\nCredits | 4\nL-T-P | 3-1-0\nPrevious Year Grade Distribution\n{{{grades}}}\nSemester | Autumn", "page": "EC60081: Rf Components And Circuit Design"}, {"chunk_id": "039f1ffc", "title": "Syllabus mentioned in ERP", "text": "Pre-requisites: EC31005Lumped circuit elements at high frequencies. S-matrix representation. RF components design: Power splitters/combiners, directional couplers, hybrids, impedance and balun transformers. RF Filter design. RF mixers, RF amplifier and Oscillator design. Amplifier Noise figure and Oscillator Phase noise. .RF instruments and measurement techniques. RF subsystem design.", "page": "EC60081: Rf Components And Circuit Design"}]