[{"chunk_id": "info_35f2b1", "title": "EE30016: Dynamics Of Physical Systems - Quick Facts", "text": "EE30016\nCourse name | Dynamics Of Physical Systems\nOffered by | Electrical Engineering\nCredits | 3\nL-T-P | 3-0-0\nPrevious Year Grade Distribution\n{{{grades}}}\nSemester | Autumn", "page": "EE30016: Dynamics Of Physical Systems"}, {"chunk_id": "923fb78a", "title": "Syllabus mentioned in ERP", "text": "System elements: character of inertial, compliant and resistive elements, voltage and current sources; Obtaining differential equations by the Newtonian method, constraints, the concept of configuration space; Obtaining differential equation for electrical circuits using Kirchoffs Laws: mesh current, node voltage, and graph theoretic methods; The Lagrangian formalism, the principle of least action, generalized coordinates; Obtaining first order differential equations: from Lagrangian equations and by the Hamiltonian method; Obtaining differential equation through bond graphs; Numerical solution of differential equations; Understanding dynamics in the state space: vector fields, local linearization around equilibrium points, analytical solution of linear differential equations, using eigenvalues and eigenvectors to solve linear equations; Dynamics of nonlinear systems: types of stable behaviour: equilibrium, limit cycle, quasi-periodic orbit, and chaos; Discrete-time dynamics: discretization of continuous-time systems, character of discrete-time state space and possible types of stable behaviour. Mechanical, Thermal and other, like biological/economic systems", "page": "EE30016: Dynamics Of Physical Systems"}]