[{"chunk_id": "info_551edd", "title": "EE60078: Analytical Instrumentation - Quick Facts", "text": "EE60078\nCourse name | ANALYTICAL INSTRUMENTATION\nOffered by | Electrical Engineering\nCredits | 3\nL-T-P | 3-0-0\nPrevious Year Grade Distribution\n{{{grades}}}\nSemester | {{{semester}}}", "page": "EE60078: Analytical Instrumentation"}, {"chunk_id": "2d8e4a3c", "title": "Syllabus mentioned in ERP", "text": "Statistical techniques:-Error analysis, distribution, confidence level, least square fitting, testing of hypothesis. Measurement of viscosity, humidity and thermal conductivity. Mass Spectroscopy. Gas Chromatography:- Principles and construction, detectors, Industrial gas chromatograph, Liquid chromatography. Ionising electrodes: -pH and ion sensitive electrodes, ISFET and chemical sensors. Absorption spectroscopy:-IR and UV spectroscopy. Non-dispersive technique of measurement; UV fluorescence spectroscopy. Emission Spectroscopy: Flame and atomic emission spectroscopy. X-ray methods of measurement: sources and detectors, X-ray absorption and florescence techniques. Chemical analysis of surface- Ion scattering spectroscopy, Auger Emission spectroscopy, ESCA. Nuclear Magnetic resonance Spectroscopy: Basic principle and its application. Environment and Pollution monitoring Instruments.", "page": "EE60078: Analytical Instrumentation"}]