[{"chunk_id": "2803153d", "title": "How to pack for a graduate school", "text": "Graduate School is a significant step in one's career. The transition from a rather free-living and fun-filled life experience as an undergraduate to a highly independent and self-caring position is an important transition. As such, when accepted by a graduate school for your higher studies, one of the first things one has to do in this transition process is to pack for your journey.", "page": "How to pack for a graduate school"}, {"chunk_id": "30412e9c", "title": "Resources", "text": "\u2022 Packing List by Vivek Rai\n\u2022 Foreign Internship Packing List", "page": "How to pack for a graduate school"}]