[{"chunk_id": "info_12dd89", "title": "HS60068: Hr Accounting - Quick Facts", "text": "HS60068\nCourse name | HR ACCOUNTING\nOffered by | Humanities & Social Sciences\nCredits | 2\nL-T-P | 2-0-0\nPrevious Year Grade Distribution\n{{{grades}}}\nSemester | {{{semester}}}", "page": "HS60068: Hr Accounting"}, {"chunk_id": "24a3269f", "title": "Syllabus mentioned in ERP", "text": "Development of state-of-the-art human resource accounting; Role and uses of human resource accounting; Corporate financial reporting; Accounting and measuring human resource costs; First and second generation accounting systems: concepts and methods; Accounting for HR value, determining HR value; Monetary and non-monetary measurement methods, first- second- and third-generation accounting systems for HR value, Implementing and designing HR accounting systems: applications for improving management, training, and personnel decisions, developing an integrated systems, advancements and future directions in HR accounting.", "page": "HS60068: Hr Accounting"}]