[{"chunk_id": "info_b5cc1f", "title": "HS60076: Compensation Management - Quick Facts", "text": "HS60076\nCourse name | COMPENSATION MANAGEMENT\nOffered by | Humanities & Social Sciences\nCredits | 2\nL-T-P | 2-0-0\nPrevious Year Grade Distribution\n{{{grades}}}\nSemester | {{{semester}}}", "page": "HS60076: Compensation Management"}, {"chunk_id": "b36e7836", "title": "Syllabus mentioned in ERP", "text": "Compensation in a knowledge-based world, compensation and non-compensation reward, pay and compensation; Organizational structure: strategic and tactical compensation issues, legislation and compensation; Job evaluation: methods of job evaluation, surveying market pay and compensation practices, designing a base pay structure, team-based pay; Measuring and paying for performance, short-term incentives, long-term incentives and wealth building, executive and international compensation, benefits and services, pay delivery administration.", "page": "HS60076: Compensation Management"}]