[{"chunk_id": "info_3d09cc", "title": "IM41012: Environmental Management - Quick Facts", "text": "IM41012\nCourse name | Environmental Management\nOffered by | Industrial & Systems Engineering\nCredits | 3\nL-T-P | 3-0-0\nPrevious Year Grade Distribution\n{{{grades}}}\nSemester | Spring", "page": "IM41012: Environmental Management"}, {"chunk_id": "bba1e57a", "title": "Syllabus mentioned in ERP", "text": "Course ContentsThe nature, scope and components of environmental management. Environmental Impact Analysis, need and importance, steps involved methods of EIA, Public participation and communication. Environmental policy analysis, Macro level and micro level, methods of policy analysis, steps involved. Environmental Management Plan (EMP) , Components of EMP, Preparation of EMP, Case Study. Organization for environmental management , example, organizational design. Environmental Legislation , Acts, Statutes and Regulations in India , case studies of litigations and implications. Environmental Audit , Components of Audit, Preparation of Audit Report , Case Study. Institutionalization of Environmental management in India , Ministry of Environment and Forest, Central Pollution Control Boards, State Pollution Control Boards, Local Bodies, their scopes, organizational and functional issues. Environmental Information Systems, Global, National, Unit,level Systems, DSS and Expert Systems, Applications. Environmental Economics, Estimation of Costs and Benefits, Cost,Benefit Analysis. Interpretation of Environmental Protection into Business Goals and Plus. Forecasting method, Markov chains and Markov Decision Processes", "page": "IM41012: Environmental Management"}]