[{"chunk_id": "info_7e3ec3", "title": "IM60022: Environmental Management - Quick Facts", "text": "IM60022\nCourse name | Environmental Management\nOffered by | Industrial & Systems Engineering\nCredits | 3\nL-T-P | 3-0-0\nPrevious Year Grade Distribution\n{{{grades}}}\nSemester | Spring", "page": "IM60022: Environmental Management"}, {"chunk_id": "0e444023", "title": "Syllabus mentioned in ERP", "text": "The nature, scope and components of environmental management. Environmental Impact Analysis- need and importance, steps involved, methods of EIA, Public participation and communication. Environmental policy analysis- Macro level and micro level, methods of policy analysis, steps involved. Environmental Management Plan (EMP) \u00c3\u00a2\u00c2\u00c2 Components of EMP, Preparation of EMP, Case Study. Organization for environmental management \u00c3\u00a2\u00c2\u00c2 example, organizational design.Environmental Legislation \u00c3\u00a2\u00c2\u00c2 Acts, Statutes and Regulations in India \u00c3\u00a2\u00c2\u00c2 case studies of litigations and implications. Environmental Audit \u00c3\u00a2\u00c2\u00c2 Components of Audit, Preparation of Audit Report \u00c3\u00a2\u00c2\u00c2 Case Study. Institutionalization of Environmental management in India \u00c3\u00a2\u00c2\u00c2 Ministry of Environment and Forest, Central Pollution Control Boards, State Pollution Control Boards, Local Bodies- their scopes, organizational and functional issues. Environmental Information Systems- Global, National, Unit-level Systems, DSS and Expert Systems, Applications. Environmental EconomicsEstimation of Costs and Benefits- Cost-Benefit Analysis. Interpretation of Environmental Protection into Business Goals and Plus. Books 1.Environmental Management in Practice: Vol 3 - Managing the Ecosystem, Bhaskar Nath, Luc Hens, Paul Compton, Dimitri Devuyst (Editors), Taylor and Francis, 1999.2.Air Pollution, H.C.V.Rao, McGraw Hill Co., 1990.", "page": "IM60022: Environmental Management"}]