[{"chunk_id": "info_f3ccfd", "title": "Jyotirmoy Chatterjee - Quick Facts", "text": "Jyotirmoy Chatterjee\nDepartment | Medical Science & Technology\nResearch Area(s) | Multimodal Imaging -Analysis for Wound & Cancer Theranostics and Regenerative Medicine Research\nYear Joined | 2007\nemail | [email protected]", "page": "Jyotirmoy Chatterjee"}, {"chunk_id": "9edb12f9", "title": "See Also", "text": "\u2022 Department of Medical Science & Technology", "page": "Jyotirmoy Chatterjee"}, {"chunk_id": "08f80c88", "title": "External links", "text": "\u2022 Jyotirmoy Chatterjee on iitkgp.ac.in", "page": "Jyotirmoy Chatterjee"}]