[{"chunk_id": "info_1da3f9", "title": "MA60004: Operating Systems Design - Quick Facts", "text": "MA60004\nCourse name | OPERATING SYSTEMS DESIGN\nOffered by | Mathematics\nCredits | 3\nL-T-P | 3-0-0\nPrevious Year Grade Distribution\n1 1 EX A B C D P F | 1 | 1 | 1 | 1 | EX | A | B | C | D | P | F\n1 | 1 | 1 | 1\n1\n1\nEX | A | B | C | D | P | F\nSemester | {{{semester}}}", "page": "MA60004: Operating Systems Design"}, {"chunk_id": "851fa726", "title": "Syllabus mentioned in ERP", "text": "Prerequisite: void CPU, Memory, file and I/O devices, Batch processing, Resource scheduling problems, their solutions and analysis, storage management, secondary storage, virtual memory, segmentation and paging. Concurrent processes and synchronization abstractions. Producer consumer problem, mutual exclusion and deadlock, properties of concurrent programs, critical section problem, semaphores, test and set, Atomic operations, Security and recovery:", "page": "MA60004: Operating Systems Design"}]