[{"chunk_id": "info_c74d1e", "title": "ME40103: Simulation Of Mechanical Systems - Quick Facts", "text": "ME40103\nCourse name | Simulation Of Mechanical Systems\nOffered by | Mechanical Engineering\nCredits | 3\nL-T-P | 3-0-0\nPrevious Year Grade Distribution\n2 3 2 4 2 2 EX A B C D P F | 2 | 2 | 3 | 3 | 2 | 2 | 4 | 4 | 2 | 2 | 2 | 2 | EX | A | B | C | D | P | F\n2 | 2 | 3 | 3 | 2 | 2 | 4 | 4 | 2 | 2 | 2 | 2\n2\n3\n2\n4\n2\n2\nEX | A | B | C | D | P | F\nSemester | Autumn", "page": "ME40103: Simulation Of Mechanical Systems"}, {"chunk_id": "e5f0fad2", "title": "Syllabus mentioned in ERP", "text": "Prerequisite ;Design of Machine ElementsEnergy Methods and variational principles. Euler-Lagranges equation for discrete and continuous systems. Hamiltons principle. Analysis of constraints - non-holonomic systems. Integration of system equations. Modelling in multi-energy domain through bond graphs. Modelling of a system of rigid bodies, structural systems, Hydraulic systems, Thermal systems, electronic and mechatronic systems. Modelling systems for control strategies and design of control strategies in physical domain. Numerical prototyping as modelling for design and synthesis using computational tools like SYMBOLS, MATLAB, ADAMs, etc.", "page": "ME40103: Simulation Of Mechanical Systems"}]