[{"chunk_id": "info_b0cc8c", "title": "TE60115: Emerging Topics In Communications Engineering - I - Quick Facts", "text": "TE60115\nCourse name | Emerging Topics In Communications Engineering - I\nOffered by | G.S Sanyal School of Telecommunication\nCredits | 4\nPrevious Year Grade Distribution\n{{{grades}}}\nSemester | {{{semester}}}", "page": "TE60115: Emerging Topics In Communications Engineering - I"}, {"chunk_id": "1979cba1", "title": "Time Table", "text": "Day | 8:00-8:55 am | 9:00-9:55 am | 10:00-10:55 am | 11:00-11:55 am | 12:00-12:55 pm | 2:00-2:55 pm | 3:00-3:55 pm | 4:00-4:55 pm | 5:00-5:55 pm\nMonday | GSCLA1\nTuesday\nWednesday | GSCLA1 | GSCLA1\nThursday | GSCLA1\nFriday", "page": "TE60115: Emerging Topics In Communications Engineering - I"}]