[
  {
    "subject": "Ambar",
    "predicate": "is an",
    "object": "LGBTQIA+ resource group"
  },
  {
    "subject": "Ambar",
    "predicate": "was founded in",
    "object": "April 2015"
  },
  {
    "subject": "Anahita Chaudhary",
    "predicate": "is a founder of",
    "object": "Ambar"
  },
  {
    "subject": "Alok Baranwal",
    "predicate": "is a founder of",
    "object": "Ambar"
  },
  {
    "subject": "Ambar",
    "predicate": "has number of members",
    "object": "15-20"
  },
  {
    "subject": "Ambar",
    "predicate": "has website",
    "object": "www.facebook.com/ambar.iitkgp"
  },
  {
    "subject": "Ambar",
    "predicate": "has contact",
    "object": "[email protected]"
  },
  {
    "subject": "Ambar",
    "predicate": "is under TSG",
    "object": "No"
  },
  {
    "subject": "Ambar",
    "predicate": "is",
    "object": "gender and sexual diversity resource group"
  },
  {
    "subject": "Ambar",
    "predicate": "serves",
    "object": "LGBTQ+ community"
  },
  {
    "subject": "LGBTQ+ community",
    "predicate": "resides in and/or is associated with",
    "object": "IIT Kharagpur Campus"
  },
  {
    "subject": "Ambar",
    "predicate": "comprises",
    "object": "current students, alumni, staff, and family of staff"
  },
  {
    "subject": "Ambar",
    "predicate": "welcomes",
    "object": "straight allies"
  },
  {
    "subject": "Ambar's vision for IIT Kharagpur",
    "predicate": "envisions a campus free from discrimination against minorities",
    "object": "minorities on the basis of gender and sexuality"
  },
  {
    "subject": "Ambar's vision for IIT Kharagpur",
    "predicate": "aims for minorities to feel safe and free",
    "object": "minorities on the basis of gender and sexuality"
  },
  {
    "subject": "Ambar's vision for IIT Kharagpur",
    "predicate": "includes existence of safe spaces for",
    "object": "people coming to terms with themselves and their sexuality"
  },
  {
    "subject": "Ambar's vision for IIT Kharagpur",
    "predicate": "commits to ending",
    "object": "sexism, homophobia, biphobia, and transphobia"
  },
  {
    "subject": "sexism, homophobia, biphobia, and transphobia",
    "predicate": "present both",
    "object": "internal and external to the campus community"
  },
  {
    "subject": "Ambar",
    "predicate": "aims to advocate for",
    "object": "rights and equality of gender and sexual minorities"
  },
  {
    "subject": "Ambar",
    "predicate": "operates within",
    "object": "IIT Kharagpur campus"
  },
  {
    "subject": "Ambar",
    "predicate": "creates awareness to increase acceptance of",
    "object": "gender and sexual minorities"
  },
  {
    "subject": "Ambar",
    "predicate": "helps people discover themselves in",
    "object": "supporting environment"
  },
  {
    "subject": "Ambar",
    "predicate": "encourages",
    "object": "campus community members"
  },
  {
    "subject": "Ambar",
    "predicate": "promotes",
    "object": "social justice"
  },
  {
    "subject": "Ambar",
    "predicate": "eliminates",
    "object": "discrimination in all its forms"
  },
  {
    "subject": "Ambar",
    "predicate": "has a policy of not revealing",
    "object": "names of its members"
  },
  {
    "subject": "Ambar",
    "predicate": "reveals names of",
    "object": "Governors"
  },
  {
    "subject": "Nikitha Bobbary",
    "predicate": "is a member of",
    "object": "Ambar"
  },
  {
    "subject": "Nikitha Bobbary",
    "predicate": "holds position",
    "object": "Governor"
  },
  {
    "subject": "Komal Arya",
    "predicate": "is a member of",
    "object": "Ambar"
  },
  {
    "subject": "Komal Arya",
    "predicate": "holds position",
    "object": "Governor"
  },
  {
    "subject": "Abhi Patidar",
    "predicate": "is a member of",
    "object": "Ambar"
  },
  {
    "subject": "Abhi Patidar",
    "predicate": "holds position",
    "object": "Governor"
  },
  {
    "subject": "Ambar",
    "predicate": "is",
    "object": "LGBT resource group of IIT Kharagpur"
  },
  {
    "subject": "Ambar",
    "predicate": "placed",
    "object": "letters in a tree with a heart shaped hole"
  },
  {
    "subject": "Ambar",
    "predicate": "placed on",
    "object": "12 September 2015"
  },
  {
    "subject": "Ambar",
    "predicate": "placed at",
    "object": "2.2"
  },
  {
    "subject": "Ambar",
    "predicate": "placed in front of",
    "object": "B C Roy Hall of Residence"
  },
  {
    "subject": "letters",
    "predicate": "were",
    "object": "sealed envelopes"
  },
  {
    "subject": "letters",
    "predicate": "contained",
    "object": "stories that touched members"
  },
  {
    "subject": "letters",
    "predicate": "were",
    "object": "mostly handwritten"
  },
  {
    "subject": "Ambar",
    "predicate": "placed",
    "object": "blank letters"
  },
  {
    "subject": "Ambar",
    "predicate": "organized",
    "object": "KASHISH Forward film screening"
  },
  {
    "subject": "KASHISH Forward film screening",
    "predicate": "associated with",
    "object": "Varta Trust"
  },
  {
    "subject": "KASHISH Forward film screening",
    "predicate": "held on",
    "object": "1 October 2015"
  },
  {
    "subject": "KASHISH Forward film screening",
    "predicate": "included",
    "object": "LGBTQ themed film screening"
  },
  {
    "subject": "KASHISH Forward film screening",
    "predicate": "included",
    "object": "panel discussion on Acceptance \u2013 Making campuses Gender and Sexuality Affirmative"
  },
  {
    "subject": "KASHISH Forward film screening",
    "predicate": "had participants",
    "object": "over 125 people"
  },
  {
    "subject": "Ambar",
    "predicate": "collaborated with",
    "object": "AIESEC"
  },
  {
    "subject": "Ambar",
    "predicate": "invited",
    "object": "Harish Iyer"
  },
  {
    "subject": "AIESEC",
    "predicate": "invited",
    "object": "Harish Iyer"
  },
  {
    "subject": "Harish Iyer",
    "predicate": "gave speech at",
    "object": "YouthSpeak Forum"
  },
  {
    "subject": "students",
    "predicate": "attended",
    "object": "YouthSpeak Forum"
  },
  {
    "subject": "Ambar",
    "predicate": "marked first public presence",
    "object": "Spring Fest 2016"
  },
  {
    "subject": "Ambar",
    "predicate": "set up",
    "object": "stall in the Arena"
  },
  {
    "subject": "stall in the Arena",
    "predicate": "occurred on",
    "object": "1 February"
  },
  {
    "subject": "Queer up with Ambar",
    "predicate": "had tagline",
    "object": "Equal People, Equal Rights, Equal Love"
  },
  {
    "subject": "Queer up with Ambar",
    "predicate": "celebrated",
    "object": "Queerness"
  },
  {
    "subject": "Queer up with Ambar",
    "predicate": "featured tasks",
    "object": "Letters of Love"
  },
  {
    "subject": "Queer up with Ambar",
    "predicate": "featured tasks",
    "object": "Sawal - Jawabb"
  },
  {
    "subject": "Queer up with Ambar",
    "predicate": "featured tasks",
    "object": "Paint your Nails"
  },
  {
    "subject": "Queer up with Ambar",
    "predicate": "featured tasks",
    "object": "Embrace ME"
  },
  {
    "subject": "Queer up with Ambar",
    "predicate": "featured tasks",
    "object": "Photo Booth"
  },
  {
    "subject": "Queer up with Ambar",
    "predicate": "featured tasks",
    "object": "Pride march"
  },
  {
    "subject": "Audience",
    "predicate": "supported",
    "object": "Queer up with Ambar"
  },
  {
    "subject": "Audience",
    "predicate": "showed appreciation for",
    "object": "Queer up with Ambar"
  },
  {
    "subject": "Audience",
    "predicate": "showed enthusiasm for",
    "object": "Queer up with Ambar"
  },
  {
    "subject": "Ambar",
    "predicate": "hosted",
    "object": "short film screening and interactive session"
  },
  {
    "subject": "short film screening and interactive session",
    "predicate": "was titled",
    "object": "Celebrating Diversity"
  },
  {
    "subject": "short film screening and interactive session",
    "predicate": "was hosted on",
    "object": "24 August 2016"
  },
  {
    "subject": "short film screening and interactive session",
    "predicate": "was used to",
    "object": "discuss and debate issues that really matter, question assumptions, biases and stereotypes, and celebrate love in all its forms"
  },
  {
    "subject": "Ambar",
    "predicate": "invited",
    "object": "Sambuddha Banerjee"
  },
  {
    "subject": "Ambar",
    "predicate": "invited",
    "object": "Sambuddha Banerjee to explore gender in cinema"
  },
  {
    "subject": "Event",
    "predicate": "occurred_on",
    "object": "12 November 2016"
  },
  {
    "subject": "Event",
    "predicate": "location",
    "object": "Pandora's Box"
  },
  {
    "subject": "Event",
    "predicate": "discussed",
    "object": "racism"
  },
  {
    "subject": "Event",
    "predicate": "discussed",
    "object": "reverse racism"
  },
  {
    "subject": "Event",
    "predicate": "discussed",
    "object": "sexism"
  },
  {
    "subject": "Event",
    "predicate": "discussed",
    "object": "reverse sexism"
  },
  {
    "subject": "Event",
    "predicate": "discussed",
    "object": "ableism"
  },
  {
    "subject": "Event",
    "predicate": "discussed",
    "object": "portrayal of various gender and sexual minorities in mainstream media"
  },
  {
    "subject": "Hollywood",
    "predicate": "was_analyzed",
    "object": "for their take on queer issues"
  },
  {
    "subject": "Bollywood",
    "predicate": "was_analyzed",
    "object": "for their take on queer issues"
  },
  {
    "subject": "Ambar",
    "predicate": "collaborated with",
    "object": "IIM Ally"
  },
  {
    "subject": "Ambar",
    "predicate": "collaborated with",
    "object": "Umeed"
  },
  {
    "subject": "IIM Ally",
    "predicate": "is resource group of",
    "object": "IIM Ahmedabad"
  },
  {
    "subject": "Umeed",
    "predicate": "is resource group in",
    "object": "IIM Kozhikode"
  },
  {
    "subject": "Ambar",
    "predicate": "conducted",
    "object": "Queer Pe Charcha"
  },
  {
    "subject": "IIM Ally",
    "predicate": "conducted",
    "object": "Queer Pe Charcha"
  },
  {
    "subject": "Umeed",
    "predicate": "conducted",
    "object": "Queer Pe Charcha"
  },
  {
    "subject": "Queer Pe Charcha",
    "predicate": "was",
    "object": "month long education series"
  },
  {
    "subject": "Queer Pe Charcha",
    "predicate": "covered",
    "object": "terms and definitions"
  },
  {
    "subject": "Queer Pe Charcha",
    "predicate": "covered",
    "object": "social issues and myths"
  },
  {
    "subject": "Queer Pe Charcha",
    "predicate": "covered",
    "object": "legal discrimination and prosecution"
  },
  {
    "subject": "Ambar",
    "predicate": "collaborated with",
    "object": "Sappho for Equality"
  },
  {
    "subject": "Ambar",
    "predicate": "conducted",
    "object": "workshop on sexual violence"
  },
  {
    "subject": "Sappho for Equality",
    "predicate": "conducted",
    "object": "workshop on sexual violence"
  },
  {
    "subject": "workshop on sexual violence",
    "predicate": "was titled",
    "object": "Sexual Violence Awareness and Understanding Gender Diversity"
  },
  {
    "subject": "workshop on sexual violence",
    "predicate": "discussed topics",
    "object": "spectra of gender and sexuality"
  },
  {
    "subject": "workshop on sexual violence",
    "predicate": "discussed topics",
    "object": "sexual assault of all kinds"
  },
  {
    "subject": "workshop on sexual violence",
    "predicate": "was conducted for",
    "object": "campus community"
  },
  {
    "subject": "Ambar",
    "predicate": "held",
    "object": "Kashish Forward"
  },
  {
    "subject": "Kashish Forward",
    "predicate": "was of",
    "object": "second edition"
  },
  {
    "subject": "Kashish Forward",
    "predicate": "took place on",
    "object": "15 October 2017"
  },
  {
    "subject": "Kashish Forward",
    "predicate": "presented",
    "object": "6 LGBTQ films"
  },
  {
    "subject": "Kashish Forward",
    "predicate": "ended with",
    "object": "interactive session"
  },
  {
    "subject": "interactive session",
    "predicate": "featured",
    "object": "Sridhar Rangayan"
  },
  {
    "subject": "Sridhar Rangayan",
    "predicate": "is",
    "object": "eminent filmmaker"
  },
  {
    "subject": "Sridhar Rangayan",
    "predicate": "is",
    "object": "festival director"
  },
  {
    "subject": "Kashish Forward",
    "predicate": "presented",
    "object": "All About Love"
  },
  {
    "subject": "Kashish Forward",
    "predicate": "presented",
    "object": "Paper and Jeans"
  },
  {
    "subject": "Kashish Forward",
    "predicate": "presented",
    "object": "Dear Drew"
  },
  {
    "subject": "Kashish Forward",
    "predicate": "presented",
    "object": "To Mum (Love, Me)"
  },
  {
    "subject": "Kashish Forward",
    "predicate": "presented",
    "object": "My Child is Gay, I am Happy"
  },
  {
    "subject": "Kashish Forward",
    "predicate": "presented",
    "object": "Any Other Day"
  },
  {
    "subject": "Ambar",
    "predicate": "invited",
    "object": "followers"
  },
  {
    "subject": "Ambar",
    "predicate": "invited on date",
    "object": "9 January 2018"
  },
  {
    "subject": "followers",
    "predicate": "write",
    "object": "personal stories"
  },
  {
    "subject": "personal stories",
    "predicate": "changed",
    "object": "perception of LGBT community"
  },
  {
    "subject": "followers",
    "predicate": "share",
    "object": "stories"
  },
  {
    "subject": "followers",
    "predicate": "share on",
    "object": "timeline"
  },
  {
    "subject": "followers",
    "predicate": "use hashtag",
    "object": "#StoriesThatMatter"
  },
  {
    "subject": "Ambar",
    "predicate": "held",
    "object": "first introductory seminar"
  },
  {
    "subject": "first introductory seminar",
    "predicate": "held on",
    "object": "20 August 2018"
  },
  {
    "subject": "first introductory seminar",
    "predicate": "talk about",
    "object": "continued reason for Ambar's existence"
  },
  {
    "subject": "first introductory seminar",
    "predicate": "talk about",
    "object": "plan forward"
  },
  {
    "subject": "first introductory seminar",
    "predicate": "include",
    "object": "interactive session"
  },
  {
    "subject": "interactive session",
    "predicate": "topic",
    "object": "history of sexuality in the Indian subcontinent"
  },
  {
    "subject": "first introductory seminar",
    "predicate": "include",
    "object": "screening of short films"
  },
  {
    "subject": "screening of short films",
    "predicate": "include",
    "object": "In a Heartbeat"
  },
  {
    "subject": "Ambar",
    "predicate": "called for",
    "object": "Pride March"
  },
  {
    "subject": "Pride March",
    "predicate": "commemorated",
    "object": "Supreme Court judgement of 6 September 2018"
  },
  {
    "subject": "Supreme Court judgement of 6 September 2018",
    "predicate": "found",
    "object": "application of Section 377 unconstitutional"
  },
  {
    "subject": "Application of Section 377",
    "predicate": "was applied to",
    "object": "consensual homosexual relationships"
  },
  {
    "subject": "Pride March",
    "predicate": "had attendance of",
    "object": "80 people"
  },
  {
    "subject": "Attendees of Pride March",
    "predicate": "included",
    "object": "students"
  },
  {
    "subject": "Attendees of Pride March",
    "predicate": "included",
    "object": "faculty"
  },
  {
    "subject": "Pride March",
    "predicate": "started from",
    "object": "Gymkhana"
  },
  {
    "subject": "Pride March",
    "predicate": "moved towards",
    "object": "Main Building"
  },
  {
    "subject": "Pride March",
    "predicate": "turned towards",
    "object": "Tikka"
  },
  {
    "subject": "Pride March",
    "predicate": "carried on to",
    "object": "Sister Nivedita Hall"
  },
  {
    "subject": "Pride March",
    "predicate": "traveled through",
    "object": "Pepsi cut"
  },
  {
    "subject": "Pride March",
    "predicate": "ended at",
    "object": "Gymkhana"
  },
  {
    "subject": "Ambar",
    "predicate": "collaborated with",
    "object": "Click KGP"
  },
  {
    "subject": "Ambar",
    "predicate": "had first collaboration with",
    "object": "Click KGP"
  },
  {
    "subject": "Ambar",
    "predicate": "organized",
    "object": "stage play Vagina Monologues"
  },
  {
    "subject": "stage play Vagina Monologues",
    "predicate": "explored",
    "object": "consensual and non-consensual sexual experiences"
  },
  {
    "subject": "stage play Vagina Monologues",
    "predicate": "explored",
    "object": "body image"
  },
  {
    "subject": "stage play Vagina Monologues",
    "predicate": "explored",
    "object": "genital mutilation"
  },
  {
    "subject": "stage play Vagina Monologues",
    "predicate": "explored",
    "object": "direct and indirect encounters with reproduction"
  },
  {
    "subject": "stage play Vagina Monologues",
    "predicate": "explored",
    "object": "fear"
  },
  {
    "subject": "stage play Vagina Monologues",
    "predicate": "explored",
    "object": "shame"
  },
  {
    "subject": "stage play Vagina Monologues",
    "predicate": "explored",
    "object": "ecstasy"
  },
  {
    "subject": "stage play Vagina Monologues",
    "predicate": "explored",
    "object": "several other topics"
  },
  {
    "subject": "performers",
    "predicate": "were",
    "object": "women"
  },
  {
    "subject": "performers",
    "predicate": "were from",
    "object": "all age groups"
  },
  {
    "subject": "performers",
    "predicate": "belonged to",
    "object": "different Societies"
  },
  {
    "subject": "performers",
    "predicate": "belonged to",
    "object": "fields of study"
  },
  {
    "subject": "Pride Week 2019",
    "predicate": "celebrated from",
    "object": "2nd-6th September 2019"
  },
  {
    "subject": "Pride Week 2019",
    "predicate": "associated with",
    "object": "Spring Fest, IIT Kharagpur"
  },
  {
    "subject": "Pride Week 2019",
    "predicate": "commemorated",
    "object": "Supreme court judgement decriminalising homosexuality"
  },
  {
    "subject": "Privilege run",
    "predicate": "conducted on",
    "object": "2nd September"
  },
  {
    "subject": "Privilege run",
    "predicate": "conducted at",
    "object": "Gymkhana"
  },
  {
    "subject": "Panel discussion",
    "predicate": "held on",
    "object": "3rd September"
  },
  {
    "subject": "Panel discussion",
    "predicate": "topic",
    "object": "Decriminalization of Section 377: What lies ahead for Inclusivity and Equality"
  },
  {
    "subject": "Panel discussion",
    "predicate": "collaborated with",
    "object": "Debating Society"
  },
  {
    "subject": "Panel discussion",
    "predicate": "collaborated with",
    "object": "Sappho for Equality"
  },
  {
    "subject": "Movie screening",
    "predicate": "held on",
    "object": "4th September"
  },
  {
    "subject": "Movie screening",
    "predicate": "collaborated with",
    "object": "Technology Filmmaking and Photography Society"
  },
  {
    "subject": "Movie screening",
    "predicate": "showcased",
    "object": "Documentaries and short films on queer lives"
  },
  {
    "subject": "Pride-themed quiz",
    "predicate": "conducted on",
    "object": "5th September"
  },
  {
    "subject": "Pride-themed quiz",
    "predicate": "collaborated with",
    "object": "Quiz Club"
  },
  {
    "subject": "Pride march",
    "predicate": "held on",
    "object": "6th September"
  },
  {
    "subject": "Pride march",
    "predicate": "involved",
    "object": "poster making"
  },
  {
    "subject": "Pride march",
    "predicate": "involved",
    "object": "face painting"
  },
  {
    "subject": "Pride march",
    "predicate": "photographed by",
    "object": "Click KGP"
  },
  {
    "subject": "Ambar",
    "predicate": "conducted",
    "object": "Quarantine Queeries"
  },
  {
    "subject": "Quarantine Queeries",
    "predicate": "is a",
    "object": "series of Instagram live sessions"
  },
  {
    "subject": "Quarantine Queeries",
    "predicate": "held on occasion of",
    "object": "Pride Month 2020"
  },
  {
    "subject": "Quarantine Queeries",
    "predicate": "included conversation with",
    "object": "Anjali Siroya"
  },
  {
    "subject": "Anjali Siroya",
    "predicate": "discussed issues of",
    "object": "Transgender people"
  },
  {
    "subject": "Quarantine Queeries",
    "predicate": "included conversation with",
    "object": "Suman Saurav"
  },
  {
    "subject": "Suman Saurav",
    "predicate": "discussed issues of",
    "object": "Dalit Bahujan Advasi Queer People"
  },
  {
    "subject": "Quarantine Queeries",
    "predicate": "included conversation with",
    "object": "Srishti Banerjee"
  },
  {
    "subject": "Srishti Banerjee",
    "predicate": "discussed issues of",
    "object": "LGBT+ people"
  },
  {
    "subject": "Quarantine Queeries",
    "predicate": "included conversation with",
    "object": "Ana"
  },
  {
    "subject": "Ana",
    "predicate": "is",
    "object": "Trans Alumna of IIT KGP"
  },
  {
    "subject": "Quarantine Queeries",
    "predicate": "included conversation with",
    "object": "Anubhuti Banerjee"
  },
  {
    "subject": "Anubhuti Banerjee",
    "predicate": "discussed creating",
    "object": "lgbt+ safe spaces in corporates"
  },
  {
    "subject": "Quarantine Queeries",
    "predicate": "included conversation with",
    "object": "Sridhar Rangayan"
  },
  {
    "subject": "Sridhar Rangayan",
    "predicate": "is",
    "object": "queer film maker"
  },
  {
    "subject": "Sridhar Rangayan",
    "predicate": "discussed",
    "object": "Queer representation in Cinema"
  },
  {
    "subject": "Ambar",
    "predicate": "conducted",
    "object": "pride-themed quiz"
  },
  {
    "subject": "pride-themed quiz",
    "predicate": "conducted with",
    "object": "Quiz Club"
  },
  {
    "subject": "pride-themed quiz",
    "predicate": "conducted on",
    "object": "30th September"
  },
  {
    "subject": "Campus Safety Workshop",
    "predicate": "was conducted on",
    "object": "26 August 2020"
  },
  {
    "subject": "Campus Safety Workshop",
    "predicate": "was conducted in collaboration with",
    "object": "Jhatkaa.org"
  },
  {
    "subject": "Campus Safety Workshop",
    "predicate": "covered",
    "object": "sexual harassment in campuses"
  },
  {
    "subject": "Campus Safety Workshop",
    "predicate": "covered",
    "object": "laws surrounding sexual harassment"
  },
  {
    "subject": "Campus Safety Workshop",
    "predicate": "covered",
    "object": "duties of Internal Complaints Committee (ICC)"
  },
  {
    "subject": "Pride Week 2020",
    "predicate": "celebrated",
    "object": "third anniversary of the historic supreme court judgement decriminalizing homosexuality"
  },
  {
    "subject": "third anniversary of the historic supreme court judgement decriminalizing homosexuality",
    "predicate": "occurred from",
    "object": "31 st August - 6 th September 2020"
  },
  {
    "subject": "Pride Week 2020",
    "predicate": "included",
    "object": "virtual events"
  },
  {
    "subject": "Queer and Queerious",
    "predicate": "featured conversation with",
    "object": "Sayli"
  },
  {
    "subject": "Sayli",
    "predicate": "discussed",
    "object": "mental health"
  },
  {
    "subject": "Sayli",
    "predicate": "discussed",
    "object": "queer affirmative counselling practice"
  },
  {
    "subject": "Queer and Queerious",
    "predicate": "featured conversation with",
    "object": "Dr. Pragati Singh"
  },
  {
    "subject": "Dr. Pragati Singh",
    "predicate": "discussed",
    "object": "Asexuality"
  },
  {
    "subject": "Dr. Pragati Singh",
    "predicate": "discussed",
    "object": "challenges faced by asexual individuals"
  },
  {
    "subject": "Art exposition",
    "predicate": "encouraged",
    "object": "Artists to send their art work with a queer theme"
  },
  {
    "subject": "Art exposition",
    "predicate": "featured",
    "object": "art work on the page"
  },
  {
    "subject": "Alumni Series",
    "predicate": "shared",
    "object": "Stories and experiences of alumni of Ambar-IIT Kharagpur"
  },
  {
    "subject": "Mythbuster series",
    "predicate": "is",
    "object": "Short video series on common myths associated with the queer community"
  },
  {
    "subject": "Ambar",
    "predicate": "put together",
    "object": "a list of resources for victims of abuse in India"
  },
  {
    "subject": "a list of resources for victims of abuse in India",
    "predicate": "includes",
    "object": "helplines"
  },
  {
    "subject": "a list of resources for victims of abuse in India",
    "predicate": "includes",
    "object": "counsellors"
  },
  {
    "subject": "a list of resources for victims of abuse in India",
    "predicate": "includes",
    "object": "legal aid"
  },
  {
    "subject": "a list of resources for victims of abuse in India",
    "predicate": "was made using",
    "object": "publicly available information"
  },
  {
    "subject": "Amrav",
    "predicate": "verified",
    "object": "content"
  },
  {
    "subject": "Ambar",
    "predicate": "informed",
    "object": "students"
  },
  {
    "subject": "Ambar",
    "predicate": "posted",
    "object": "Facebook post"
  }
]